as3ninja/__init__.py
as3ninja/__main__.py
as3ninja/api.py
as3ninja/cli.py
as3ninja/declaration.py
as3ninja/exceptions.py
as3ninja/gitget.py
as3ninja/jinja2/__init__.py
as3ninja/jinja2/filterfunctions.py
as3ninja/jinja2/filters.py
as3ninja/jinja2/functions.py
as3ninja/jinja2/j2ninja.py
as3ninja/jinja2/tests.py
as3ninja/schema/__init__.py
as3ninja/schema/as3schema.py
as3ninja/schema/formatcheckers.py
as3ninja/settings.py
as3ninja/templateconfiguration.py
as3ninja/types.py
as3ninja/utils.py
as3ninja/vault.py
docs/Makefile
docs/_heading.rst
docs/_static/_api.gif
docs/_static/_api_demo.gif
docs/_static/_cli.svg
docs/_static/_docker_cli.svg
docs/_static/_docker_ephemeral.svg
docs/_static/_docker_persistent.svg
docs/_static/_httpie_api.svg
docs/_static/logo.png
docs/as3ninja.jinja2.rst
docs/as3ninja.rst
docs/as3ninja.schema.rst
docs/as3ninja_settings.rst
docs/authors.rst
docs/concepts.rst
docs/conf.py
docs/contributing.rst
docs/examples.rst_
docs/history.rst
docs/index.rst
docs/installation.rst_
docs/modules.rst
docs/readme.rst
docs/requirements.txt
docs/support.rst
docs/templating.rst
docs/todos.rst
docs/usage.rst
docs/vault.rst
tests/__init__.py
tests/install.sh
tests/pytest.ini
tests/reporting.sh
tests/run_tests.sh
tests/test_api.py
tests/test_cli.py
tests/test_declaration.py
tests/test_gitget.py
tests/test_jinja2_filters.py
tests/test_jinja2_functions.py
tests/test_jinja2_j2ninja.py
tests/test_main.py
tests/test_schema_as3schema.py
tests/test_schema_formatcheckers.py
tests/test_settings.py
tests/test_templateconfiguration.py
tests/test_types.py
tests/test_utils.py
tests/test_vault.py
tests/utils.py
as3ninja-0.6.1.dist-info/LICENSE
as3ninja-0.6.1.dist-info/WHEEL
as3ninja-0.6.1.dist-info/METADATA
as3ninja-0.6.1.dist-info/entry_points.txt
as3ninja-0.6.1.dist-info/RECORD
