Metadata-Version: 2.1
Name: as3ninja
Version: 0.6.1
Summary: AS3 Ninja is a templating and validation engine for your AS3 declarations providing a CLI and Swagger REST API
Home-page: https://github.com/simonkowallik/as3ninja
License: ISC
Keywords: F5,AS3,DevOps,Security
Author: Simon Kowallik
Author-email: github@simonkowallik.com
Maintainer: Simon Kowallik
Maintainer-email: github@simonkowallik.com
Requires-Python: >=3.8,<4.0
Classifier: Development Status :: 4 - Beta
Classifier: Intended Audience :: Developers
Classifier: Intended Audience :: Information Technology
Classifier: Intended Audience :: System Administrators
Classifier: License :: OSI Approved
Classifier: License :: OSI Approved :: ISC License (ISCL)
Classifier: Natural Language :: English
Classifier: Operating System :: OS Independent
Classifier: Programming Language :: Python
Classifier: Programming Language :: Python :: 3
Classifier: Programming Language :: Python :: 3.8
Classifier: Programming Language :: Python :: 3.9
Classifier: Programming Language :: Python :: 3.10
Classifier: Programming Language :: Python :: 3.11
Classifier: Programming Language :: Python :: 3
Classifier: Programming Language :: Python :: 3.7
Classifier: Programming Language :: Python :: 3.8
Classifier: Topic :: Internet
Classifier: Topic :: Security
Classifier: Topic :: Software Development
Classifier: Topic :: Software Development :: Code Generators
Classifier: Topic :: Software Development :: Libraries
Classifier: Topic :: Software Development :: Libraries :: Python Modules
Classifier: Topic :: Software Development :: Version Control
Classifier: Topic :: Software Development :: Version Control :: Git
Classifier: Topic :: System
Classifier: Topic :: System :: Installation/Setup
Classifier: Topic :: System :: Networking
Classifier: Topic :: System :: Systems Administration
Requires-Dist: click (>=8.1.3,<9.0.0)
Requires-Dist: fastapi (>=0.79.1,<1)
Requires-Dist: hvac (>=0.11.2,<0.12.0)
Requires-Dist: jinja2 (>=3.1.2,<4.0.0)
Requires-Dist: jsonschema (>=4.17.0,<5.0.0)
Requires-Dist: loguru (>=0.6.0,<1)
Requires-Dist: pydantic (>=1.9.2,<2.0.0)
Requires-Dist: pyyaml (>=6.0,<7.0)
Requires-Dist: six (>=1.16.0,<2.0.0)
Requires-Dist: uvicorn (>=0.18.2,<0.19.0)
Project-URL: Documentation, https://as3ninja.readthedocs.io/
Project-URL: Repository, https://github.com/simonkowallik/as3ninja
Project-URL: issues, https://github.com/simonkowallik/as3ninja/issues
